{"data":[{"pk":22469,"externalId":14028344,"gameSlug":"24","overall":94,"maxOverall":94,"image":{"url":"https://media.mut.gg/cdn-cgi/image/format=auto,width=100,height=100,quality=80,fit=cover,gravity=top/24/mutdb/playeritem/14028344.png"},"fullImage":{"url":"https://media.mut.gg/cdn-cgi/image/format=auto,width=208,height=356,quality=80,fit=cover,gravity=top/24/mutdb/playeritem/14028344.png"},"borderImage":{"url":"https://media.mut.gg/cdn-cgi/image/format=auto,width=300,height=401,quality=80,fit=cover,gravity=top/24/mutdb/border/324.png"},"socialImage":{"url":"https://media.mut.gg/24/mutdb/playeritem/social_14028344_L1662uv.webp"},"cardImage":{"url":"https://media.mut.gg/24/mutdb/playeritem/card_14028344.webp"},"firstName":"Chris","lastName":"Johnson","team":{"id":31,"name":"Titans","location":"Tennessee","abbreviation":"TEN","primaryHexColor":"#0C2340","secondaryHexColor":"#4B92DB","urlSlug":"tennessee-titans"},"program":{"id":243,"name":"Legends","image":{"url":"https://media.mut.gg/24/mutdb/program/140.png"},"hexColor":"#000000"},"canAuction":true,"canTrade":true,"isMaxedOvr":false,"hasPowerUp":false,"isLtd":false,"tier":1,"position":{"id":2,"name":"Half Back","abbreviation":"HB","basePosition":{"id":2,"name":"Half Back","abbreviation":"HB"}},"url":"/players/28344-chris-johnson/24-14028344/","archetype":{"name":"Elusive Back - HB","nameWithoutPosition":"Elusive Back"},"pcPrice":351500,"pcPriceDisplay":"352K","pcPercentChange":"0.0000","pcPercentChangeDisplay":"0.00","xb1Price":414000,"xb1PriceDisplay":"414K","xb1PercentChange":"0.0000","xb1PercentChangeDisplay":"0.00","xbsxPrice":351000,"xbsxPriceDisplay":"351K","xbsxPercentChange":"0.0000","xbsxPercentChangeDisplay":"0.00","ps4Price":405000,"ps4PriceDisplay":"405K","ps4PercentChange":"0.0000","ps4PercentChangeDisplay":"0.00","ps5Price":351000,"ps5PriceDisplay":"351K","ps5PercentChange":"0.0000","ps5PercentChangeDisplay":"0.00","displayChemAbbreviation":"ten","displayChemImageUrl":"https://media.mut.gg/24/mutdb/chemistry/6300_VHS4cfF.xsl","displayChemName":"Tennessee Titans","releaseDate":"2023-12-30T15:39:35.639648Z","player":{"id":3139,"externalId":28344,"firstName":"Chris","lastName":"Johnson"},"abilitySlots":[{"id":1841597,"name":"X-Factor Abilities","slotNumber":0,"abilityType":2,"abilities":[{"id":25543014,"abilityId":7090,"points":0},{"id":25543015,"abilityId":7071,"points":0},{"id":25543016,"abilityId":7076,"points":0},{"id":25543017,"abilityId":7091,"points":0},{"id":25543018,"abilityId":7066,"points":0},{"id":25543019,"abilityId":7074,"points":0},{"id":25543020,"abilityId":7070,"points":0},{"id":25543021,"abilityId":7089,"points":0}]},{"id":1841598,"name":"Tier 1 Abilities","slotNumber":1,"abilityType":2,"abilities":[{"id":25543022,"abilityId":7002,"points":1},{"id":25543023,"abilityId":7052,"points":1},{"id":25543024,"abilityId":6965,"points":1},{"id":25543025,"abilityId":6943,"points":1},{"id":25543026,"abilityId":7047,"points":1},{"id":25543027,"abilityId":6961,"points":1},{"id":25543028,"abilityId":6969,"points":1},{"id":25543029,"abilityId":7147,"points":1},{"id":25543030,"abilityId":7054,"points":1},{"id":25543031,"abilityId":7137,"points":1},{"id":25543032,"abilityId":7018,"points":1}]},{"id":1841599,"name":"Tier 2 Abilities","slotNumber":2,"abilityType":2,"abilities":[{"id":25543033,"abilityId":7002,"points":1},{"id":25543034,"abilityId":7362,"points":2},{"id":25543035,"abilityId":6976,"points":2},{"id":25543036,"abilityId":7010,"points":2},{"id":25543037,"abilityId":6930,"points":2},{"id":25543038,"abilityId":6948,"points":2},{"id":25543039,"abilityId":7054,"points":1},{"id":25543040,"abilityId":6931,"points":2}]},{"id":1841600,"name":"Tier 3 Abilities","slotNumber":3,"abilityType":2,"abilities":[{"id":25543041,"abilityId":6976,"points":2},{"id":25543042,"abilityId":7005,"points":2},{"id":25543043,"abilityId":7010,"points":2},{"id":25543044,"abilityId":7016,"points":2},{"id":25543045,"abilityId":6948,"points":2},{"id":25543046,"abilityId":6931,"points":2}]},{"id":1841601,"name":"Tier 4 Abilities","slotNumber":4,"abilityType":2,"abilities":[{"id":25543047,"abilityId":6984,"points":3},{"id":25543048,"abilityId":7020,"points":3},{"id":25543049,"abilityId":7005,"points":2}]},{"id":1841602,"name":"Player-Specific Abilities","slotNumber":5,"abilityType":2,"abilities":[{"id":25543050,"abilityId":7010,"points":1},{"id":25543051,"abilityId":7005,"points":1},{"id":25543052,"abilityId":6980,"points":2}]}],"upgradeTiers":[{"key":"16-22469-1","tierNumber":1,"overall":94,"title":"Team Chemistry And Ability Slot","description":"Add Training to unlock the Team Chemistry and Ability Slots.","currencyCost":5,"currencyRefundAmount":2,"currencyId":4,"programId":244,"upgradeStep":null,"requiredEntity":null,"refundScalar":"0.50"}],"upgradeTierDisplays":[],"availableChemistry":[{"id":3046,"externalId":6300,"name":"Tennessee Titans","flavorText":"Boosts all Titans players.","boostTarget":"Tennessee","sortOrder":1031,"hidden":false,"image":{"url":"https://media.mut.gg/24/mutdb/chemistry/6300_VHS4cfF.xsl"},"baseChemTeamId":31,"chemistryType":1,"displaySlug":"ten","themeTeamSlug":"tennessee-titans","count":1},{"id":3034,"externalId":6180,"name":"New York Jets","flavorText":"Boosts all Jets players.","boostTarget":"New York","sortOrder":1019,"hidden":false,"image":{"url":"https://media.mut.gg/24/mutdb/chemistry/6180_bklqKIb.xsl"},"baseChemTeamId":19,"chemistryType":1,"displaySlug":"nyj","themeTeamSlug":"new-york-jets","count":1},{"id":3023,"externalId":6070,"name":"Arizona Cardinals","flavorText":"Boosts all Cardinals players.","boostTarget":"Arizona","sortOrder":1007,"hidden":false,"image":{"url":"https://media.mut.gg/24/mutdb/chemistry/6070_ZgCiDja.xsl"},"baseChemTeamId":8,"chemistryType":1,"displaySlug":"ari","themeTeamSlug":"arizona-cardinals","count":1}],"stockChemistry":[{"id":3046,"externalId":6300,"name":"Tennessee Titans","flavorText":"Boosts all Titans players.","boostTarget":"Tennessee","sortOrder":1031,"hidden":false,"image":{"url":"https://media.mut.gg/24/mutdb/chemistry/6300_VHS4cfF.xsl"},"baseChemTeamId":31,"chemistryType":1,"displaySlug":"ten","themeTeamSlug":"tennessee-titans","count":1}],"defaultChemistry":{"id":3046,"externalId":6300,"name":"Tennessee Titans","flavorText":"Boosts all Titans players.","boostTarget":"Tennessee","sortOrder":1031,"hidden":false,"image":{"url":"https://media.mut.gg/24/mutdb/chemistry/6300_VHS4cfF.xsl"},"baseChemTeamId":31,"chemistryType":1,"displaySlug":"ten","themeTeamSlug":"tennessee-titans"},"heightInches":71,"weightPounds":203,"traits":[{"fieldName":"trait_aggressive_catches","displayName":"Aggressive Catches","displayValue":"No"},{"fieldName":"trait_clutch","displayName":"Clutch","displayValue":"No"},{"fieldName":"trait_covers_the_ball","displayName":"Covers the Ball","displayValue":"Brace For All Hits"},{"fieldName":"trait_drops_open_passes","displayName":"Drops Open Passes","displayValue":"No"},{"fieldName":"trait_fights_for_extra_yards","displayName":"Fights for Extra Yards","displayValue":"No"},{"fieldName":"trait_high_motor","displayName":"High Motor","displayValue":"No"},{"fieldName":"trait_makes_sideline_catches","displayName":"Makes Sideline Catches","displayValue":"No"},{"fieldName":"trait_penalty","displayName":"Penalty","displayValue":"Normal"},{"fieldName":"trait_possession_catches","displayName":"Possession Catches","displayValue":"No"},{"fieldName":"trait_rac_catches","displayName":"RAC Catches","displayValue":"No"}],"acceleration":96,"agility":94,"awareness":94,"ballCarrierVision":94,"blockShedding":11,"breakSack":18,"breakTackle":94,"carrying":80,"catchInTraffic":60,"catching":80,"changeOfDirection":95,"deepRouteRunning":55,"deepThrowAccuracy":20,"finesseMoves":10,"hitPower":20,"impactBlocking":57,"injury":93,"jukeMove":94,"jumping":90,"kickAccuracy":25,"kickPower":25,"kickReturn":65,"leadBlock":52,"manCoverage":15,"mediumRouteRunning":70,"mediumThrowAccuracy":30,"passBlock":50,"passBlockFinesse":42,"passBlockPower":41,"playAction":15,"playRecognition":20,"powerMoves":10,"press":20,"pursuit":40,"release":66,"runBlock":58,"runBlockFinesse":40,"runBlockPower":42,"shortRouteRunning":82,"shortThrowAccuracy":35,"spectacularCatch":73,"speed":96,"spinMove":93,"stamina":94,"stiffArm":75,"strength":62,"tackle":22,"throwAccuracy":30,"throwPower":30,"throwUnderPressure":14,"throwingOnTheRun":15,"toughness":71,"trucking":72,"zoneCoverage":20}],"totalCount":1}