{"data":[{"pk":21120,"externalId":15502527,"gameSlug":"24","overall":87,"maxOverall":87,"image":{"url":"https://media.mut.gg/cdn-cgi/image/format=auto,width=100,height=100,quality=80,fit=cover,gravity=top/24/mutdb/playeritem/15502527.png"},"fullImage":{"url":"https://media.mut.gg/cdn-cgi/image/format=auto,width=208,height=356,quality=80,fit=cover,gravity=top/24/mutdb/playeritem/15502527.png"},"borderImage":{"url":"https://media.mut.gg/cdn-cgi/image/format=auto,width=300,height=401,quality=80,fit=cover,gravity=top/24/mutdb/border/325.png"},"socialImage":{"url":"https://media.mut.gg/24/mutdb/playeritem/social_15502527_b6Pln9P.webp"},"cardImage":{"url":"https://media.mut.gg/24/mutdb/playeritem/card_15502527_HjrWsNN.webp"},"firstName":"L. Williams","lastName":"Big Cat","team":{"id":17,"name":"Giants","location":"New York","abbreviation":"NYG","primaryHexColor":"#0B2265","secondaryHexColor":"#A71930","urlSlug":"new-york-giants"},"program":{"id":234,"name":"AKA","image":{"url":"https://media.mut.gg/24/mutdb/program/155_W3jcdnQ.png"},"hexColor":"#000000"},"canAuction":true,"canTrade":true,"isMaxedOvr":false,"hasPowerUp":false,"isLtd":false,"tier":1,"position":{"id":12,"name":"Right End","abbreviation":"RE","basePosition":{"id":9,"name":"Defensive End","abbreviation":"DE"}},"url":"/players/2527-leonard-williams/24-15502527/","archetype":{"name":"Run Stopper - DE","nameWithoutPosition":"Run Stopper"},"pcPrice":2300,"pcPriceDisplay":"2,300","pcPercentChange":"0.0000","pcPercentChangeDisplay":"0.00","xb1Price":3400,"xb1PriceDisplay":"3,400","xb1PercentChange":"-8.1100","xb1PercentChangeDisplay":"-8.11","xbsxPrice":1450,"xbsxPriceDisplay":"1,450","xbsxPercentChange":"7.4100","xbsxPercentChangeDisplay":"7.41","ps4Price":4200,"ps4PriceDisplay":"4,200","ps4PercentChange":"-15.2000","ps4PercentChangeDisplay":"-15.2","ps5Price":1450,"ps5PriceDisplay":"1,450","ps5PercentChange":"7.4100","ps5PercentChangeDisplay":"7.41","displayChemAbbreviation":"nyg","displayChemImageUrl":"https://media.mut.gg/24/mutdb/chemistry/6160_Vx5EtQe.xsl","displayChemName":"New York Giants","releaseDate":"2023-08-28T17:35:10.511232Z","player":{"id":182,"externalId":2527,"firstName":"Leonard","lastName":"Williams"},"abilitySlots":[{"id":1829038,"name":"X-Factor Abilities","slotNumber":0,"abilityType":1,"abilities":[{"id":25436734,"abilityId":7087,"points":0},{"id":25436735,"abilityId":7079,"points":0},{"id":25436736,"abilityId":7060,"points":0},{"id":25436737,"abilityId":7084,"points":0},{"id":25436738,"abilityId":9264,"points":0},{"id":25436739,"abilityId":7077,"points":0},{"id":25436740,"abilityId":7075,"points":0},{"id":25436741,"abilityId":7080,"points":0},{"id":25436742,"abilityId":9226,"points":2},{"id":25436743,"abilityId":7072,"points":0},{"id":25436744,"abilityId":9232,"points":2}]},{"id":1829039,"name":"Tier 1 Abilities","slotNumber":1,"abilityType":2,"abilities":[{"id":25436745,"abilityId":7052,"points":1},{"id":25436746,"abilityId":6965,"points":1},{"id":25436747,"abilityId":6943,"points":1},{"id":25436748,"abilityId":6961,"points":1},{"id":25436749,"abilityId":6969,"points":1},{"id":25436750,"abilityId":7035,"points":1},{"id":25436751,"abilityId":7147,"points":1},{"id":25436752,"abilityId":7137,"points":1},{"id":25436753,"abilityId":7008,"points":1},{"id":25436754,"abilityId":7044,"points":1},{"id":25436755,"abilityId":7055,"points":1},{"id":25436756,"abilityId":7042,"points":1}]},{"id":1829040,"name":"Tier 2 Abilities","slotNumber":2,"abilityType":2,"abilities":[{"id":25436757,"abilityId":7048,"points":2},{"id":25436758,"abilityId":7989,"points":2},{"id":25436759,"abilityId":7024,"points":2},{"id":25436760,"abilityId":7030,"points":2},{"id":25436761,"abilityId":7037,"points":2},{"id":25436762,"abilityId":9250,"points":3},{"id":25436763,"abilityId":7041,"points":2},{"id":25436764,"abilityId":7034,"points":2},{"id":25436765,"abilityId":7004,"points":2},{"id":25436766,"abilityId":6986,"points":2},{"id":25436767,"abilityId":6999,"points":2},{"id":25436768,"abilityId":7038,"points":2}]}],"upgradeTiers":[{"key":"16-21120-1","tierNumber":1,"overall":87,"title":"Team Chemistry And Ability Slot","description":"Add Training to unlock the Team Chemistry and Ability Slots.","currencyCost":5,"currencyRefundAmount":2,"currencyId":4,"programId":244,"upgradeStep":null,"requiredEntity":null,"refundScalar":"0.50"},{"key":"16-21120-2","tierNumber":2,"overall":87,"title":"Ability Slot","description":"Add Training to unlock a NEW AKA X-Factor Upgrade! Run Stuffer charges up 1 down faster.","currencyCost":680,"currencyRefundAmount":340,"currencyId":4,"programId":244,"upgradeStep":{"id":15741,"mods":{"stamina":1}},"requiredEntity":null,"refundScalar":"0.50"}],"upgradeTierDisplays":[],"availableChemistry":[{"id":3034,"externalId":6180,"name":"New York Jets","flavorText":"Boosts all Jets players.","boostTarget":"New York","sortOrder":1019,"hidden":false,"image":{"url":"https://media.mut.gg/24/mutdb/chemistry/6180_bklqKIb.xsl"},"baseChemTeamId":19,"chemistryType":1,"displaySlug":"nyj","themeTeamSlug":"new-york-jets","count":1},{"id":3032,"externalId":6160,"name":"New York Giants","flavorText":"Boosts all Giants players.","boostTarget":"New York","sortOrder":1017,"hidden":false,"image":{"url":"https://media.mut.gg/24/mutdb/chemistry/6160_Vx5EtQe.xsl"},"baseChemTeamId":17,"chemistryType":1,"displaySlug":"nyg","themeTeamSlug":"new-york-giants","count":1},{"id":3044,"externalId":6280,"name":"Seattle Seahawks","flavorText":"Boosts all Seahawks players.","boostTarget":"Seattle","sortOrder":1028,"hidden":false,"image":{"url":"https://media.mut.gg/24/mutdb/chemistry/6280_bNBGh30.xsl"},"baseChemTeamId":29,"chemistryType":1,"displaySlug":"sea","themeTeamSlug":"seattle-seahawks","count":1}],"stockChemistry":[{"id":3032,"externalId":6160,"name":"New York Giants","flavorText":"Boosts all Giants players.","boostTarget":"New York","sortOrder":1017,"hidden":false,"image":{"url":"https://media.mut.gg/24/mutdb/chemistry/6160_Vx5EtQe.xsl"},"baseChemTeamId":17,"chemistryType":1,"displaySlug":"nyg","themeTeamSlug":"new-york-giants","count":1}],"defaultChemistry":{"id":3032,"externalId":6160,"name":"New York Giants","flavorText":"Boosts all Giants players.","boostTarget":"New York","sortOrder":1017,"hidden":false,"image":{"url":"https://media.mut.gg/24/mutdb/chemistry/6160_Vx5EtQe.xsl"},"baseChemTeamId":17,"chemistryType":1,"displaySlug":"nyg","themeTeamSlug":"new-york-giants"},"heightInches":77,"weightPounds":302,"traits":[{"fieldName":"trait_big_hitter","displayName":"Big Hitter","displayValue":"No"},{"fieldName":"trait_high_motor","displayName":"High Motor","displayValue":"Yes"},{"fieldName":"trait_utilizes_bull_rush_move","displayName":"Pass Rush Bull Rush Move","displayValue":"Yes"},{"fieldName":"trait_utilizes_spin_move","displayName":"Pass Rush Spin Move","displayValue":"No"},{"fieldName":"trait_utilizes_swim_move","displayName":"Pass Rush Swim Move","displayValue":"No"},{"fieldName":"trait_penalty","displayName":"Penalty","displayValue":"Normal"},{"fieldName":"trait_strips_ball","displayName":"Strips Ball","displayValue":"No"}],"acceleration":80,"agility":65,"awareness":86,"ballCarrierVision":28,"blockShedding":87,"breakSack":10,"breakTackle":10,"carrying":45,"catchInTraffic":27,"catching":35,"changeOfDirection":54,"deepRouteRunning":10,"deepThrowAccuracy":10,"finesseMoves":77,"hitPower":84,"impactBlocking":88,"injury":87,"jukeMove":34,"jumping":67,"kickAccuracy":10,"kickPower":10,"kickReturn":14,"leadBlock":10,"manCoverage":21,"mediumRouteRunning":10,"mediumThrowAccuracy":10,"passBlock":35,"passBlockFinesse":35,"passBlockPower":35,"playAction":10,"playRecognition":86,"powerMoves":88,"press":18,"pursuit":86,"release":10,"runBlock":35,"runBlockFinesse":35,"runBlockPower":35,"shortRouteRunning":10,"shortThrowAccuracy":10,"spectacularCatch":23,"speed":76,"spinMove":24,"stamina":85,"stiffArm":40,"strength":86,"tackle":90,"throwAccuracy":20,"throwPower":25,"throwUnderPressure":10,"throwingOnTheRun":10,"toughness":85,"trucking":39,"zoneCoverage":27}],"totalCount":1}