{"data":[{"pk":21588,"externalId":15600692,"gameSlug":"24","overall":87,"maxOverall":87,"image":{"url":"https://media.mut.gg/cdn-cgi/image/format=auto,width=100,height=100,quality=80,fit=cover,gravity=top/24/mutdb/playeritem/15600692.png"},"fullImage":{"url":"https://media.mut.gg/cdn-cgi/image/format=auto,width=208,height=356,quality=80,fit=cover,gravity=top/24/mutdb/playeritem/15600692.png"},"borderImage":{"url":"https://media.mut.gg/cdn-cgi/image/format=auto,width=300,height=401,quality=80,fit=cover,gravity=top/24/mutdb/border/331.png"},"socialImage":{"url":"https://media.mut.gg/24/mutdb/playeritem/social_15600692_HD6kVHT.webp"},"cardImage":{"url":"https://media.mut.gg/24/mutdb/playeritem/card_15600692_RKxFZFF.webp"},"firstName":"Cornelius","lastName":"Bennett","team":{"id":4,"name":"Bills","location":"Buffalo","abbreviation":"BUF","primaryHexColor":"#00338D","secondaryHexColor":"#C60C30","urlSlug":"buffalo-bills"},"program":{"id":234,"name":"AKA","image":{"url":"https://media.mut.gg/24/mutdb/program/155_W3jcdnQ.png"},"hexColor":"#000000"},"canAuction":true,"canTrade":true,"isMaxedOvr":false,"hasPowerUp":false,"isLtd":false,"tier":1,"position":{"id":14,"name":"Left Outside Linebacker","abbreviation":"LOLB","basePosition":{"id":11,"name":"Outside Linebacker","abbreviation":"OLB"}},"url":"/players/692-cornelius-bennett/24-15600692/","archetype":{"name":"Run Stopper - OLB","nameWithoutPosition":"Run Stopper"},"pcPrice":2950,"pcPriceDisplay":"2,950","pcPercentChange":"1.7200","pcPercentChangeDisplay":"1.72","xb1Price":1675,"xb1PriceDisplay":"1,675","xb1PercentChange":"-9.4600","xb1PercentChangeDisplay":"-9.46","xbsxPrice":1350,"xbsxPriceDisplay":"1,350","xbsxPercentChange":"0.0000","xbsxPercentChangeDisplay":"0.00","ps4Price":2475,"ps4PriceDisplay":"2,475","ps4PercentChange":"-10.8000","ps4PercentChangeDisplay":"-10.8","ps5Price":1350,"ps5PriceDisplay":"1,350","ps5PercentChange":"0.0000","ps5PercentChangeDisplay":"0.00","displayChemAbbreviation":"buf","displayChemImageUrl":"https://media.mut.gg/24/mutdb/chemistry/6030_qanhKY3.xsl","displayChemName":"Buffalo Bills","releaseDate":"2023-10-16T17:34:53.830459Z","player":{"id":512,"externalId":692,"firstName":"Cornelius","lastName":"Bennett"},"abilitySlots":[{"id":1829560,"name":"X-Factor Abilities","slotNumber":0,"abilityType":1,"abilities":[{"id":25441419,"abilityId":7086,"points":0},{"id":25441420,"abilityId":9264,"points":0},{"id":25441421,"abilityId":7060,"points":0},{"id":25441422,"abilityId":7080,"points":0},{"id":25441423,"abilityId":7075,"points":0},{"id":25441424,"abilityId":7077,"points":0},{"id":25441425,"abilityId":7079,"points":0},{"id":25441426,"abilityId":7068,"points":0},{"id":25441427,"abilityId":7072,"points":0},{"id":25441428,"abilityId":7073,"points":0}]},{"id":1829561,"name":"Tier 1 Abilities","slotNumber":1,"abilityType":2,"abilities":[{"id":25441429,"abilityId":7049,"points":1},{"id":25441430,"abilityId":7052,"points":1},{"id":25441431,"abilityId":6965,"points":1},{"id":25441432,"abilityId":6943,"points":1},{"id":25441433,"abilityId":6961,"points":1},{"id":25441434,"abilityId":6969,"points":1},{"id":25441435,"abilityId":7035,"points":1},{"id":25441436,"abilityId":7050,"points":1},{"id":25441437,"abilityId":7147,"points":1},{"id":25441438,"abilityId":7137,"points":1},{"id":25441439,"abilityId":7008,"points":1},{"id":25441440,"abilityId":7018,"points":1},{"id":25441441,"abilityId":7044,"points":1},{"id":25441442,"abilityId":7055,"points":1},{"id":25441443,"abilityId":7042,"points":1}]},{"id":1829562,"name":"Tier 2 Abilities","slotNumber":2,"abilityType":2,"abilities":[{"id":25441444,"abilityId":7048,"points":2},{"id":25441445,"abilityId":7040,"points":2},{"id":25441446,"abilityId":7989,"points":2},{"id":25441447,"abilityId":7024,"points":2},{"id":25441448,"abilityId":7030,"points":2},{"id":25441449,"abilityId":7035,"points":1},{"id":25441450,"abilityId":7017,"points":2},{"id":25441451,"abilityId":7050,"points":1},{"id":25441452,"abilityId":7004,"points":2},{"id":25441453,"abilityId":6986,"points":2},{"id":25441454,"abilityId":7013,"points":2}]}],"upgradeTiers":[{"key":"16-21588-1","tierNumber":1,"overall":87,"title":"Team Ability Slot","description":"Add Training to unlock the Team Ability Slot.","currencyCost":5,"currencyRefundAmount":2,"currencyId":4,"programId":244,"upgradeStep":null,"requiredEntity":null,"refundScalar":"0.50"}],"upgradeTierDisplays":[],"availableChemistry":[{"id":3019,"externalId":6030,"name":"Buffalo Bills","flavorText":"Boosts all Bills players.","boostTarget":"Buffalo","sortOrder":1003,"hidden":false,"image":{"url":"https://media.mut.gg/24/mutdb/chemistry/6030_qanhKY3.xsl"},"baseChemTeamId":4,"chemistryType":1,"displaySlug":"buf","themeTeamSlug":"buffalo-bills","count":1}],"stockChemistry":[{"id":3019,"externalId":6030,"name":"Buffalo Bills","flavorText":"Boosts all Bills players.","boostTarget":"Buffalo","sortOrder":1003,"hidden":false,"image":{"url":"https://media.mut.gg/24/mutdb/chemistry/6030_qanhKY3.xsl"},"baseChemTeamId":4,"chemistryType":1,"displaySlug":"buf","themeTeamSlug":"buffalo-bills","count":1}],"defaultChemistry":{"id":3019,"externalId":6030,"name":"Buffalo Bills","flavorText":"Boosts all Bills players.","boostTarget":"Buffalo","sortOrder":1003,"hidden":false,"image":{"url":"https://media.mut.gg/24/mutdb/chemistry/6030_qanhKY3.xsl"},"baseChemTeamId":4,"chemistryType":1,"displaySlug":"buf","themeTeamSlug":"buffalo-bills"},"heightInches":75,"weightPounds":240,"traits":[{"fieldName":"trait_big_hitter","displayName":"Big Hitter","displayValue":"Yes"},{"fieldName":"trait_clutch","displayName":"Clutch","displayValue":"Yes"},{"fieldName":"trait_high_motor","displayName":"High Motor","displayValue":"Yes"},{"fieldName":"trait_lb_style","displayName":"LB Style","displayValue":"Balanced"},{"fieldName":"trait_utilizes_bull_rush_move","displayName":"Pass Rush Bull Rush Move","displayValue":"Yes"},{"fieldName":"trait_utilizes_spin_move","displayName":"Pass Rush Spin Move","displayValue":"Yes"},{"fieldName":"trait_utilizes_swim_move","displayName":"Pass Rush Swim Move","displayValue":"Yes"},{"fieldName":"trait_penalty","displayName":"Penalty","displayValue":"Disciplined"},{"fieldName":"trait_plays_ball_in_the_air","displayName":"Plays Ball in the Air","displayValue":"Aggressive"},{"fieldName":"trait_strips_ball","displayName":"Strips Ball","displayValue":"Yes"}],"acceleration":81,"agility":80,"awareness":86,"ballCarrierVision":48,"blockShedding":88,"breakSack":20,"breakTackle":33,"carrying":63,"catchInTraffic":54,"catching":77,"changeOfDirection":72,"deepRouteRunning":5,"deepThrowAccuracy":6,"finesseMoves":75,"hitPower":81,"impactBlocking":87,"injury":89,"jukeMove":38,"jumping":89,"kickAccuracy":15,"kickPower":13,"kickReturn":18,"leadBlock":26,"manCoverage":52,"mediumRouteRunning":5,"mediumThrowAccuracy":6,"passBlock":45,"passBlockFinesse":45,"passBlockPower":45,"playAction":6,"playRecognition":86,"powerMoves":87,"press":51,"pursuit":79,"release":18,"runBlock":45,"runBlockFinesse":45,"runBlockPower":45,"shortRouteRunning":15,"shortThrowAccuracy":6,"spectacularCatch":57,"speed":86,"spinMove":33,"stamina":89,"stiffArm":43,"strength":89,"tackle":86,"throwAccuracy":44,"throwPower":24,"throwUnderPressure":12,"throwingOnTheRun":5,"toughness":89,"trucking":58,"zoneCoverage":62}],"totalCount":1}