{"data":[{"pk":22875,"externalId":35520403,"gameSlug":"24","overall":92,"maxOverall":92,"image":{"url":"https://media.mut.gg/cdn-cgi/image/format=auto,width=100,height=100,quality=80,fit=cover,gravity=top/24/mutdb/playeritem/35520403.png"},"fullImage":{"url":"https://media.mut.gg/cdn-cgi/image/format=auto,width=208,height=356,quality=80,fit=cover,gravity=top/24/mutdb/playeritem/35520403.png"},"borderImage":{"url":"https://media.mut.gg/cdn-cgi/image/format=auto,width=300,height=401,quality=80,fit=cover,gravity=top/24/mutdb/border/381.png"},"socialImage":{"url":"https://media.mut.gg/24/mutdb/playeritem/social_35520403_zC9Q6JW.webp"},"cardImage":{"url":"https://media.mut.gg/24/mutdb/playeritem/card_35520403.webp"},"firstName":"Charles","lastName":"Omenihu","team":{"id":10,"name":"Chiefs","location":"Kansas City","abbreviation":"KC","primaryHexColor":"#E31837","secondaryHexColor":"#FFB81C","urlSlug":"kansas-city-chiefs"},"program":{"id":276,"name":"Super Bowl Present","image":{"url":"https://media.mut.gg/24/mutdb/program/355.png"},"hexColor":"#000000"},"canAuction":true,"canTrade":true,"isMaxedOvr":false,"hasPowerUp":false,"isLtd":false,"tier":1,"position":{"id":12,"name":"Right End","abbreviation":"RE","basePosition":{"id":9,"name":"Defensive End","abbreviation":"DE"}},"url":"/players/20403-charles-omenihu/24-35520403/","archetype":{"name":"Power Rusher - DE","nameWithoutPosition":"Power Rusher"},"pcPrice":13000,"pcPriceDisplay":"13K","pcPercentChange":"0.0000","pcPercentChangeDisplay":"0.00","xb1Price":13750,"xb1PriceDisplay":"13.8K","xb1PercentChange":"0.0000","xb1PercentChangeDisplay":"0.00","xbsxPrice":13000,"xbsxPriceDisplay":"13K","xbsxPercentChange":"0.0000","xbsxPercentChangeDisplay":"0.00","ps4Price":14450,"ps4PriceDisplay":"14.4K","ps4PercentChange":"0.0000","ps4PercentChangeDisplay":"0.00","ps5Price":13000,"ps5PriceDisplay":"13K","ps5PercentChange":"0.0000","ps5PercentChangeDisplay":"0.00","displayChemAbbreviation":"kc","displayChemImageUrl":"https://media.mut.gg/24/mutdb/chemistry/6090_mvm4TvS.xsl","displayChemName":"Kansas City Chiefs","releaseDate":"2024-02-08T18:37:54.077165Z","player":{"id":1135,"externalId":20403,"firstName":"Charles","lastName":"Omenihu"},"abilitySlots":[{"id":1834434,"name":"X-Factor Abilities","slotNumber":0,"abilityType":2,"abilities":[{"id":25481695,"abilityId":7087,"points":0},{"id":25481696,"abilityId":9264,"points":0},{"id":25481697,"abilityId":7060,"points":0},{"id":25481698,"abilityId":7080,"points":0},{"id":25481699,"abilityId":7075,"points":0},{"id":25481700,"abilityId":7084,"points":0},{"id":25481701,"abilityId":7077,"points":0},{"id":25481702,"abilityId":7079,"points":0},{"id":25481703,"abilityId":7072,"points":0}]},{"id":1834435,"name":"Tier 1 Abilities","slotNumber":1,"abilityType":2,"abilities":[{"id":25481704,"abilityId":7052,"points":1},{"id":25481705,"abilityId":6965,"points":1},{"id":25481706,"abilityId":6943,"points":1},{"id":25481707,"abilityId":6961,"points":1},{"id":25481708,"abilityId":6969,"points":1},{"id":25481709,"abilityId":7035,"points":1},{"id":25481710,"abilityId":7147,"points":1},{"id":25481711,"abilityId":7137,"points":1},{"id":25481712,"abilityId":7008,"points":1},{"id":25481713,"abilityId":7044,"points":1},{"id":25481714,"abilityId":7055,"points":1},{"id":25481715,"abilityId":7042,"points":1}]},{"id":1834436,"name":"Tier 2 Abilities","slotNumber":2,"abilityType":2,"abilities":[{"id":25481716,"abilityId":7048,"points":2},{"id":25481717,"abilityId":7989,"points":2},{"id":25481718,"abilityId":8000,"points":2},{"id":25481719,"abilityId":7024,"points":2},{"id":25481720,"abilityId":7030,"points":2},{"id":25481721,"abilityId":7037,"points":2},{"id":25481722,"abilityId":9250,"points":3},{"id":25481723,"abilityId":7041,"points":2},{"id":25481724,"abilityId":7004,"points":2},{"id":25481725,"abilityId":6986,"points":2},{"id":25481726,"abilityId":7013,"points":2},{"id":25481727,"abilityId":7038,"points":2}]},{"id":1834437,"name":"Tier 3 Abilities","slotNumber":3,"abilityType":2,"abilities":[{"id":25481728,"abilityId":7040,"points":2},{"id":25481729,"abilityId":7039,"points":2},{"id":25481730,"abilityId":7036,"points":3},{"id":25481731,"abilityId":6987,"points":3},{"id":25481732,"abilityId":7046,"points":2},{"id":25481733,"abilityId":7024,"points":2},{"id":25481734,"abilityId":7030,"points":2},{"id":25481735,"abilityId":9250,"points":3},{"id":25481736,"abilityId":6986,"points":2},{"id":25481737,"abilityId":7013,"points":2},{"id":25481738,"abilityId":7038,"points":2}]}],"upgradeTiers":[{"key":"16-22875-1","tierNumber":1,"overall":92,"title":"Team Chemistry And Ability Slot","description":"Add Training to unlock the Team Chemistry and Ability Slots.","currencyCost":5,"currencyRefundAmount":2,"currencyId":4,"programId":244,"upgradeStep":null,"requiredEntity":null,"refundScalar":"0.50"}],"upgradeTierDisplays":[],"availableChemistry":[{"id":3048,"externalId":6320,"name":"Houston Texans","flavorText":"Boosts all Texans players.","boostTarget":"Houston","sortOrder":1030,"hidden":false,"image":{"url":"https://media.mut.gg/24/mutdb/chemistry/6320_UdU0E3L.xsl"},"baseChemTeamId":33,"chemistryType":1,"displaySlug":"hou","themeTeamSlug":"houston-texans","count":1},{"id":3031,"externalId":6150,"name":"San Francisco 49ers","flavorText":"Boosts all 49ers players.","boostTarget":"San Francisco","sortOrder":1016,"hidden":false,"image":{"url":"https://media.mut.gg/24/mutdb/chemistry/6150_gInIpZz.xsl"},"baseChemTeamId":16,"chemistryType":1,"displaySlug":"sf","themeTeamSlug":"san-francisco-49ers","count":1},{"id":3025,"externalId":6090,"name":"Kansas City Chiefs","flavorText":"Boosts all Chiefs players.","boostTarget":"Kansas City","sortOrder":1009,"hidden":false,"image":{"url":"https://media.mut.gg/24/mutdb/chemistry/6090_mvm4TvS.xsl"},"baseChemTeamId":10,"chemistryType":1,"displaySlug":"kc","themeTeamSlug":"kansas-city-chiefs","count":1},{"id":3333,"externalId":6370,"name":"MUT 24 Super Bowl","flavorText":"Boosts all MUT 24 Super Bowl Past and Present Players.","boostTarget":"Super Bowl","sortOrder":1,"hidden":false,"image":{"url":"https://media.mut.gg/24/mutdb/chemistry/6370.png"},"baseChemTeamId":null,"chemistryType":2,"displaySlug":"super-bowl","themeTeamSlug":"super-bowl","count":2}],"stockChemistry":[{"id":3025,"externalId":6090,"name":"Kansas City Chiefs","flavorText":"Boosts all Chiefs players.","boostTarget":"Kansas City","sortOrder":1009,"hidden":false,"image":{"url":"https://media.mut.gg/24/mutdb/chemistry/6090_mvm4TvS.xsl"},"baseChemTeamId":10,"chemistryType":1,"displaySlug":"kc","themeTeamSlug":"kansas-city-chiefs","count":1}],"defaultChemistry":{"id":3025,"externalId":6090,"name":"Kansas City Chiefs","flavorText":"Boosts all Chiefs players.","boostTarget":"Kansas City","sortOrder":1009,"hidden":false,"image":{"url":"https://media.mut.gg/24/mutdb/chemistry/6090_mvm4TvS.xsl"},"baseChemTeamId":10,"chemistryType":1,"displaySlug":"kc","themeTeamSlug":"kansas-city-chiefs"},"heightInches":77,"weightPounds":280,"traits":[{"fieldName":"trait_big_hitter","displayName":"Big Hitter","displayValue":"No"},{"fieldName":"trait_high_motor","displayName":"High Motor","displayValue":"Yes"},{"fieldName":"trait_utilizes_bull_rush_move","displayName":"Pass Rush Bull Rush Move","displayValue":"Yes"},{"fieldName":"trait_utilizes_spin_move","displayName":"Pass Rush Spin Move","displayValue":"No"},{"fieldName":"trait_utilizes_swim_move","displayName":"Pass Rush Swim Move","displayValue":"No"},{"fieldName":"trait_penalty","displayName":"Penalty","displayValue":"Normal"},{"fieldName":"trait_strips_ball","displayName":"Strips Ball","displayValue":"Yes"}],"acceleration":87,"agility":82,"awareness":90,"ballCarrierVision":23,"blockShedding":91,"breakSack":10,"breakTackle":13,"carrying":31,"catchInTraffic":46,"catching":56,"changeOfDirection":75,"deepRouteRunning":10,"deepThrowAccuracy":10,"finesseMoves":86,"hitPower":85,"impactBlocking":81,"injury":92,"jukeMove":18,"jumping":93,"kickAccuracy":10,"kickPower":10,"kickReturn":16,"leadBlock":10,"manCoverage":39,"mediumRouteRunning":10,"mediumThrowAccuracy":10,"passBlock":35,"passBlockFinesse":35,"passBlockPower":35,"playAction":10,"playRecognition":90,"powerMoves":92,"press":30,"pursuit":89,"release":16,"runBlock":35,"runBlockFinesse":35,"runBlockPower":35,"shortRouteRunning":11,"shortThrowAccuracy":10,"spectacularCatch":43,"speed":82,"spinMove":10,"stamina":87,"stiffArm":31,"strength":92,"tackle":88,"throwAccuracy":11,"throwPower":18,"throwUnderPressure":10,"throwingOnTheRun":10,"toughness":84,"trucking":32,"zoneCoverage":47}],"totalCount":1}