{"data":[{"pk":23823,"externalId":45531644,"gameSlug":"24","overall":97,"maxOverall":97,"image":{"url":"https://media.mut.gg/cdn-cgi/image/format=auto,width=100,height=100,quality=80,fit=cover,gravity=top/24/mutdb/playeritem/45531644.png"},"fullImage":{"url":"https://media.mut.gg/cdn-cgi/image/format=auto,width=208,height=356,quality=80,fit=cover,gravity=top/24/mutdb/playeritem/45531644.png"},"borderImage":{"url":"https://media.mut.gg/cdn-cgi/image/format=auto,width=300,height=401,quality=80,fit=cover,gravity=top/24/mutdb/border/411.png"},"socialImage":{"url":"https://media.mut.gg/24/mutdb/playeritem/social_45531644_5QLlR59.webp"},"cardImage":{"url":"https://media.mut.gg/24/mutdb/playeritem/card_45531644.webp"},"firstName":"Jared","lastName":"Verse","team":{"id":25,"name":"Rams","location":"Los Angeles","abbreviation":"LAR","primaryHexColor":"#003594","secondaryHexColor":"#FFD100","urlSlug":"los-angeles-rams"},"program":{"id":289,"name":"NFL Draft Night","image":{"url":"https://media.mut.gg/24/mutdb/program/456.png"},"hexColor":"#000000"},"canAuction":true,"canTrade":true,"isMaxedOvr":false,"hasPowerUp":false,"isLtd":false,"tier":1,"position":{"id":12,"name":"Right End","abbreviation":"RE","basePosition":{"id":9,"name":"Defensive End","abbreviation":"DE"}},"url":"/players/31644-jared-verse/24-45531644/","archetype":{"name":"Power Rusher - DE","nameWithoutPosition":"Power Rusher"},"pcPrice":130000,"pcPriceDisplay":"130K","pcPercentChange":"0.0000","pcPercentChangeDisplay":"0.00","xb1Price":156000,"xb1PriceDisplay":"156K","xb1PercentChange":"2.6300","xb1PercentChangeDisplay":"2.63","xbsxPrice":130000,"xbsxPriceDisplay":"130K","xbsxPercentChange":"0.0000","xbsxPercentChangeDisplay":"0.00","ps4Price":149500,"ps4PriceDisplay":"150K","ps4PercentChange":"-6.5600","ps4PercentChangeDisplay":"-6.56","ps5Price":147000,"ps5PriceDisplay":"147K","ps5PercentChange":"13.1000","ps5PercentChangeDisplay":"13.1","displayChemAbbreviation":"lar","displayChemImageUrl":"https://media.mut.gg/24/mutdb/chemistry/6240_lJ3IuBJ.xsl","displayChemName":"Los Angeles Rams","releaseDate":"2024-04-26T03:59:20.043315Z","player":{"id":4505,"externalId":31644,"firstName":"Jared","lastName":"Verse"},"abilitySlots":[{"id":1843320,"name":"X-Factor Abilities","slotNumber":0,"abilityType":2,"abilities":[{"id":25558570,"abilityId":7087,"points":0},{"id":25558571,"abilityId":9264,"points":0},{"id":25558572,"abilityId":7060,"points":0},{"id":25558573,"abilityId":7080,"points":0},{"id":25558574,"abilityId":7075,"points":0},{"id":25558575,"abilityId":7084,"points":0},{"id":25558576,"abilityId":7077,"points":0},{"id":25558577,"abilityId":7079,"points":0},{"id":25558578,"abilityId":7072,"points":0}]},{"id":1843321,"name":"Tier 1 Abilities","slotNumber":1,"abilityType":2,"abilities":[{"id":25558579,"abilityId":7052,"points":1},{"id":25558580,"abilityId":6965,"points":1},{"id":25558581,"abilityId":6943,"points":1},{"id":25558582,"abilityId":6961,"points":1},{"id":25558583,"abilityId":6969,"points":1},{"id":25558584,"abilityId":7035,"points":1},{"id":25558585,"abilityId":7147,"points":1},{"id":25558586,"abilityId":7137,"points":1},{"id":25558587,"abilityId":7008,"points":1},{"id":25558588,"abilityId":7044,"points":1},{"id":25558589,"abilityId":7055,"points":1},{"id":25558590,"abilityId":7042,"points":1}]},{"id":1843322,"name":"Tier 2 Abilities","slotNumber":2,"abilityType":2,"abilities":[{"id":25558591,"abilityId":7048,"points":2},{"id":25558592,"abilityId":7999,"points":2},{"id":25558593,"abilityId":7989,"points":2},{"id":25558594,"abilityId":8000,"points":2},{"id":25558595,"abilityId":7024,"points":2},{"id":25558596,"abilityId":7030,"points":2},{"id":25558597,"abilityId":7037,"points":2},{"id":25558598,"abilityId":9250,"points":3},{"id":25558599,"abilityId":7041,"points":2},{"id":25558600,"abilityId":7032,"points":2},{"id":25558601,"abilityId":7034,"points":2},{"id":25558602,"abilityId":7004,"points":2},{"id":25558603,"abilityId":6986,"points":2},{"id":25558604,"abilityId":6999,"points":2},{"id":25558605,"abilityId":7013,"points":2},{"id":25558606,"abilityId":7007,"points":2},{"id":25558607,"abilityId":7038,"points":2}]},{"id":1843323,"name":"Tier 3 Abilities","slotNumber":3,"abilityType":2,"abilities":[{"id":25558608,"abilityId":7040,"points":2},{"id":25558609,"abilityId":7039,"points":2},{"id":25558610,"abilityId":7036,"points":3},{"id":25558611,"abilityId":6987,"points":3},{"id":25558612,"abilityId":7046,"points":2},{"id":25558613,"abilityId":6998,"points":2},{"id":25558614,"abilityId":7024,"points":2},{"id":25558615,"abilityId":7030,"points":2},{"id":25558616,"abilityId":7031,"points":2},{"id":25558617,"abilityId":9250,"points":3},{"id":25558618,"abilityId":7032,"points":2},{"id":25558619,"abilityId":6986,"points":2},{"id":25558620,"abilityId":6999,"points":2},{"id":25558621,"abilityId":7013,"points":2},{"id":25558622,"abilityId":7038,"points":2}]},{"id":1843324,"name":"Tier 4 Abilities","slotNumber":4,"abilityType":2,"abilities":[{"id":25558623,"abilityId":7039,"points":2},{"id":25558624,"abilityId":7036,"points":3},{"id":25558625,"abilityId":6940,"points":4},{"id":25558626,"abilityId":7031,"points":2},{"id":25558627,"abilityId":7017,"points":2},{"id":25558628,"abilityId":6993,"points":3},{"id":25558629,"abilityId":6996,"points":3}]},{"id":1843325,"name":"Player-Specific Abilities","slotNumber":5,"abilityType":2,"abilities":[{"id":25558630,"abilityId":7040,"points":1},{"id":25558631,"abilityId":6987,"points":0},{"id":25558632,"abilityId":6999,"points":1}]}],"upgradeTiers":[{"key":"16-23823-1","tierNumber":1,"overall":97,"title":"Team Ability Slot","description":"Add Training to unlock the Team Ability Slot.","currencyCost":5,"currencyRefundAmount":2,"currencyId":4,"programId":244,"upgradeStep":null,"requiredEntity":null,"refundScalar":"0.50"}],"upgradeTierDisplays":[],"availableChemistry":[{"id":3040,"externalId":6240,"name":"Los Angeles Rams","flavorText":"Boosts all Rams players.","boostTarget":"Los Angeles","sortOrder":1024,"hidden":false,"image":{"url":"https://media.mut.gg/24/mutdb/chemistry/6240_lJ3IuBJ.xsl"},"baseChemTeamId":25,"chemistryType":1,"displaySlug":"lar","themeTeamSlug":"los-angeles-rams","count":1}],"stockChemistry":[{"id":3040,"externalId":6240,"name":"Los Angeles Rams","flavorText":"Boosts all Rams players.","boostTarget":"Los Angeles","sortOrder":1024,"hidden":false,"image":{"url":"https://media.mut.gg/24/mutdb/chemistry/6240_lJ3IuBJ.xsl"},"baseChemTeamId":25,"chemistryType":1,"displaySlug":"lar","themeTeamSlug":"los-angeles-rams","count":1}],"defaultChemistry":{"id":3040,"externalId":6240,"name":"Los Angeles Rams","flavorText":"Boosts all Rams players.","boostTarget":"Los Angeles","sortOrder":1024,"hidden":false,"image":{"url":"https://media.mut.gg/24/mutdb/chemistry/6240_lJ3IuBJ.xsl"},"baseChemTeamId":25,"chemistryType":1,"displaySlug":"lar","themeTeamSlug":"los-angeles-rams"},"heightInches":76,"weightPounds":254,"traits":[{"fieldName":"trait_big_hitter","displayName":"Big Hitter","displayValue":"No"},{"fieldName":"trait_high_motor","displayName":"High Motor","displayValue":"Yes"},{"fieldName":"trait_utilizes_bull_rush_move","displayName":"Pass Rush Bull Rush Move","displayValue":"Yes"},{"fieldName":"trait_utilizes_spin_move","displayName":"Pass Rush Spin Move","displayValue":"No"},{"fieldName":"trait_utilizes_swim_move","displayName":"Pass Rush Swim Move","displayValue":"Yes"},{"fieldName":"trait_penalty","displayName":"Penalty","displayValue":"Undisciplined"},{"fieldName":"trait_strips_ball","displayName":"Strips Ball","displayValue":"Yes"}],"acceleration":90,"agility":87,"awareness":92,"ballCarrierVision":19,"blockShedding":95,"breakSack":12,"breakTackle":10,"carrying":45,"catchInTraffic":15,"catching":46,"changeOfDirection":86,"deepRouteRunning":5,"deepThrowAccuracy":6,"finesseMoves":88,"hitPower":94,"impactBlocking":95,"injury":93,"jukeMove":20,"jumping":88,"kickAccuracy":21,"kickPower":15,"kickReturn":10,"leadBlock":12,"manCoverage":46,"mediumRouteRunning":8,"mediumThrowAccuracy":6,"passBlock":45,"passBlockFinesse":45,"passBlockPower":45,"playAction":6,"playRecognition":92,"powerMoves":97,"press":20,"pursuit":94,"release":15,"runBlock":45,"runBlockFinesse":45,"runBlockPower":45,"shortRouteRunning":15,"shortThrowAccuracy":6,"spectacularCatch":15,"speed":95,"spinMove":15,"stamina":94,"stiffArm":35,"strength":97,"tackle":97,"throwAccuracy":16,"throwPower":19,"throwUnderPressure":14,"throwingOnTheRun":6,"toughness":87,"trucking":29,"zoneCoverage":57}],"totalCount":1}