{"data":[{"pk":23928,"externalId":52122211,"gameSlug":"24","overall":97,"maxOverall":97,"image":{"url":"https://media.mut.gg/cdn-cgi/image/format=auto,width=100,height=100,quality=80,fit=cover,gravity=top/24/mutdb/playeritem/52122211.png"},"fullImage":{"url":"https://media.mut.gg/cdn-cgi/image/format=auto,width=208,height=356,quality=80,fit=cover,gravity=top/24/mutdb/playeritem/52122211.png"},"borderImage":{"url":"https://media.mut.gg/cdn-cgi/image/format=auto,width=300,height=401,quality=80,fit=cover,gravity=top/24/mutdb/border/443.png"},"socialImage":{"url":"https://media.mut.gg/24/mutdb/playeritem/social_52122211.webp"},"cardImage":{"url":"https://media.mut.gg/24/mutdb/playeritem/card_52122211.webp"},"firstName":"Coby","lastName":"Bryant","team":{"id":29,"name":"Seahawks","location":"Seattle","abbreviation":"SEA","primaryHexColor":"#002244","secondaryHexColor":"#69BE28","urlSlug":"seattle-seahawks"},"program":{"id":291,"name":"Infinite Flux","image":{"url":"https://media.mut.gg/24/mutdb/program/520.png"},"hexColor":"#000000"},"canAuction":true,"canTrade":true,"isMaxedOvr":false,"hasPowerUp":false,"isLtd":false,"tier":1,"position":{"id":17,"name":"Cornerback","abbreviation":"CB","basePosition":{"id":13,"name":"Cornerback","abbreviation":"CB"}},"url":"/players/22211-coby-bryant/24-52122211/","archetype":{"name":"Zone - CB","nameWithoutPosition":"Zone"},"pcPrice":200000,"pcPriceDisplay":"200K","pcPercentChange":"0.0000","pcPercentChangeDisplay":"0.00","xb1Price":200000,"xb1PriceDisplay":"200K","xb1PercentChange":"-4.3100","xb1PercentChangeDisplay":"-4.31","xbsxPrice":191000,"xbsxPriceDisplay":"191K","xbsxPercentChange":"-2.5500","xbsxPercentChangeDisplay":"-2.55","ps4Price":220000,"ps4PriceDisplay":"220K","ps4PercentChange":"4.7600","ps4PercentChangeDisplay":"4.76","ps5Price":195000,"ps5PriceDisplay":"195K","ps5PercentChange":"-2.5000","ps5PercentChangeDisplay":"-2.50","displayChemAbbreviation":"sea","displayChemImageUrl":"https://media.mut.gg/24/mutdb/chemistry/6280_bNBGh30.xsl","displayChemName":"Seattle Seahawks","releaseDate":"2024-05-02T17:30:25.524403Z","player":{"id":3425,"externalId":22211,"firstName":"Coby","lastName":"Bryant"},"abilitySlots":[{"id":1843112,"name":"X-Factor Abilities","slotNumber":0,"abilityType":2,"abilities":[{"id":25556683,"abilityId":7092,"points":0},{"id":25556684,"abilityId":7068,"points":0},{"id":25556685,"abilityId":7085,"points":0},{"id":25556686,"abilityId":7073,"points":0}]},{"id":1843113,"name":"Tier 1 Abilities","slotNumber":1,"abilityType":2,"abilities":[{"id":25556687,"abilityId":7049,"points":1},{"id":25556688,"abilityId":7052,"points":1},{"id":25556689,"abilityId":6965,"points":1},{"id":25556690,"abilityId":6943,"points":1},{"id":25556691,"abilityId":6961,"points":1},{"id":25556692,"abilityId":6969,"points":1},{"id":25556693,"abilityId":7035,"points":1},{"id":25556694,"abilityId":7050,"points":1},{"id":25556695,"abilityId":7147,"points":1},{"id":25556696,"abilityId":7137,"points":1},{"id":25556697,"abilityId":7018,"points":1},{"id":25556698,"abilityId":7055,"points":1}]},{"id":1843114,"name":"Tier 2 Abilities","slotNumber":2,"abilityType":2,"abilities":[{"id":25556699,"abilityId":7049,"points":1},{"id":25556700,"abilityId":6988,"points":2},{"id":25556701,"abilityId":6989,"points":3},{"id":25556702,"abilityId":8307,"points":2},{"id":25556703,"abilityId":7050,"points":1},{"id":25556704,"abilityId":6934,"points":2},{"id":25556705,"abilityId":7055,"points":1},{"id":25556706,"abilityId":6958,"points":2}]},{"id":1843115,"name":"Tier 3 Abilities","slotNumber":3,"abilityType":2,"abilities":[{"id":25556707,"abilityId":6977,"points":2},{"id":25556708,"abilityId":6992,"points":2},{"id":25556709,"abilityId":6988,"points":2},{"id":25556710,"abilityId":7017,"points":2},{"id":25556711,"abilityId":6989,"points":3},{"id":25556712,"abilityId":7050,"points":1},{"id":25556713,"abilityId":6934,"points":2},{"id":25556714,"abilityId":6958,"points":2}]},{"id":1843116,"name":"Tier 4 Abilities","slotNumber":4,"abilityType":2,"abilities":[{"id":25556715,"abilityId":6977,"points":2},{"id":25556716,"abilityId":6992,"points":2},{"id":25556717,"abilityId":6990,"points":3},{"id":25556718,"abilityId":7053,"points":3},{"id":25556719,"abilityId":6988,"points":2},{"id":25556720,"abilityId":6989,"points":3}]}],"upgradeTiers":[{"key":"16-23928-1","tierNumber":1,"overall":97,"title":"Team Chemistry And Ability Slot","description":"Add Training to unlock the Team Chemistry and Ability Slots.","currencyCost":5,"currencyRefundAmount":2,"currencyId":4,"programId":244,"upgradeStep":null,"requiredEntity":null,"refundScalar":"0.50"}],"upgradeTierDisplays":[],"availableChemistry":[{"id":3044,"externalId":6280,"name":"Seattle Seahawks","flavorText":"Boosts all Seahawks players.","boostTarget":"Seattle","sortOrder":1028,"hidden":false,"image":{"url":"https://media.mut.gg/24/mutdb/chemistry/6280_bNBGh30.xsl"},"baseChemTeamId":29,"chemistryType":1,"displaySlug":"sea","themeTeamSlug":"seattle-seahawks","count":1}],"stockChemistry":[{"id":3044,"externalId":6280,"name":"Seattle Seahawks","flavorText":"Boosts all Seahawks players.","boostTarget":"Seattle","sortOrder":1028,"hidden":false,"image":{"url":"https://media.mut.gg/24/mutdb/chemistry/6280_bNBGh30.xsl"},"baseChemTeamId":29,"chemistryType":1,"displaySlug":"sea","themeTeamSlug":"seattle-seahawks","count":1},{"id":3554,"externalId":521,"name":"IF Coby Bryant","flavorText":"Boost all Infinite Flux Players","boostTarget":"Boosts Infinite Flux Players","sortOrder":8100230,"hidden":false,"image":{"url":"https://media.mut.gg/24/mutdb/chemistry/521.png"},"baseChemTeamId":null,"chemistryType":null,"displaySlug":null,"themeTeamSlug":null,"count":1}],"defaultChemistry":{"id":3044,"externalId":6280,"name":"Seattle Seahawks","flavorText":"Boosts all Seahawks players.","boostTarget":"Seattle","sortOrder":1028,"hidden":false,"image":{"url":"https://media.mut.gg/24/mutdb/chemistry/6280_bNBGh30.xsl"},"baseChemTeamId":29,"chemistryType":1,"displaySlug":"sea","themeTeamSlug":"seattle-seahawks"},"heightInches":73,"weightPounds":193,"traits":[{"fieldName":"trait_big_hitter","displayName":"Big Hitter","displayValue":"No"},{"fieldName":"trait_clutch","displayName":"Clutch","displayValue":"No"},{"fieldName":"trait_high_motor","displayName":"High Motor","displayValue":"No"},{"fieldName":"trait_lb_style","displayName":"LB Style","displayValue":"Cover LB"},{"fieldName":"trait_utilizes_bull_rush_move","displayName":"Pass Rush Bull Rush Move","displayValue":"No"},{"fieldName":"trait_utilizes_spin_move","displayName":"Pass Rush Spin Move","displayValue":"No"},{"fieldName":"trait_utilizes_swim_move","displayName":"Pass Rush Swim Move","displayValue":"No"},{"fieldName":"trait_penalty","displayName":"Penalty","displayValue":"Normal"},{"fieldName":"trait_plays_ball_in_the_air","displayName":"Plays Ball in the Air","displayValue":"Aggressive"},{"fieldName":"trait_strips_ball","displayName":"Strips Ball","displayValue":"Yes"}],"acceleration":96,"agility":94,"awareness":96,"ballCarrierVision":55,"blockShedding":58,"breakSack":10,"breakTackle":39,"carrying":52,"catchInTraffic":71,"catching":85,"changeOfDirection":93,"deepRouteRunning":10,"deepThrowAccuracy":10,"finesseMoves":35,"hitPower":76,"impactBlocking":49,"injury":94,"jukeMove":64,"jumping":90,"kickAccuracy":10,"kickPower":11,"kickReturn":67,"leadBlock":10,"manCoverage":88,"mediumRouteRunning":10,"mediumThrowAccuracy":10,"passBlock":10,"passBlockFinesse":24,"passBlockPower":23,"playAction":10,"playRecognition":96,"powerMoves":28,"press":93,"pursuit":80,"release":10,"runBlock":10,"runBlockFinesse":24,"runBlockPower":23,"shortRouteRunning":14,"shortThrowAccuracy":10,"spectacularCatch":78,"speed":96,"spinMove":56,"stamina":96,"stiffArm":23,"strength":77,"tackle":72,"throwAccuracy":16,"throwPower":17,"throwUnderPressure":10,"throwingOnTheRun":10,"toughness":83,"trucking":19,"zoneCoverage":96}],"totalCount":1}